[
  {
    "inputs": [
      {
        "internalType": "address",
        "name": "_smartPool",
        "type": "address"
      },
      {
        "internalType": "address",
        "name": "_wrappingContract",
        "type": "address"
      },
      {
        "internalType": "address",
        "name": "_treasury",
        "type": "address"
      },
      {
        "internalType": "address",
        "name": "_foldToken",
        "type": "address"
      },
      {
        "internalType": "uint256",
        "name": "_protocolFee",
        "type": "uint256"
      }
    ],
    "stateMutability": "nonpayable",
    "type": "constructor"
  },
  {
    "inputs": [],
    "name": "LIQ_FEE_DECIMALS",
    "outputs": [
      {
        "internalType": "uint256",
        "name": "",
        "type": "uint256"
      }
    ],
    "stateMutability": "view",
    "type": "function"
  },
  {
    "inputs": [],
    "name": "MAX_OUT_RATIO",
    "outputs": [
      {
        "internalType": "uint256",
        "name": "",
        "type": "uint256"
      }
    ],
    "stateMutability": "view",
    "type": "function"
  },
  {
    "inputs": [],
    "name": "PROTOCOL_FEE_DECIMALS",
    "outputs": [
      {
        "internalType": "uint256",
        "name": "",
        "type": "uint256"
      }
    ],
    "stateMutability": "view",
    "type": "function"
  },
  {
    "inputs": [
      {
        "internalType": "address",
        "name": "token",
        "type": "address"
      }
    ],
    "name": "collectFeesToDAO",
    "outputs": [],
    "stateMutability": "nonpayable",
    "type": "function"
  },
  {
    "inputs": [
      {
        "internalType": "address",
        "name": "tokenIn",
        "type": "address"
      },
      {
        "internalType": "uint256",
        "name": "tokenAmountIn",
        "type": "uint256"
      },
      {
        "internalType": "uint256",
        "name": "minPoolAmountOut",
        "type": "uint256"
      },
      {
        "internalType": "uint256",
        "name": "liquidationFee",
        "type": "uint256"
      }
    ],
    "name": "deposit",
    "outputs": [],
    "stateMutability": "nonpayable",
    "type": "function"
  },
  {
    "inputs": [
      {
        "internalType": "uint256",
        "name": "poolAmountOut",
        "type": "uint256"
      },
      {
        "internalType": "uint256[]",
        "name": "maxTokensAmountIn",
        "type": "uint256[]"
      },
      {
        "internalType": "uint256",
        "name": "liquidationFee",
        "type": "uint256"
      }
    ],
    "name": "depositAll",
    "outputs": [],
    "stateMutability": "nonpayable",
    "type": "function"
  },
  {
    "inputs": [],
    "name": "getPoolTokens",
    "outputs": [
      {
        "internalType": "address[]",
        "name": "",
        "type": "address[]"
      }
    ],
    "stateMutability": "view",
    "type": "function"
  },
  {
    "inputs": [
      {
        "internalType": "address",
        "name": "tokenOut",
        "type": "address"
      },
      {
        "internalType": "uint256",
        "name": "tokenAmountOut",
        "type": "uint256"
      },
      {
        "internalType": "uint256",
        "name": "maxPoolAmountIn",
        "type": "uint256"
      }
    ],
    "name": "getFoldAmountInSingle",
    "outputs": [
      {
        "internalType": "uint256",
        "name": "poolAmountIn",
        "type": "uint256"
      }
    ],
    "stateMutability": "view",
    "type": "function"
  },
  {
    "inputs": [
      {
        "internalType": "address",
        "name": "tokenIn",
        "type": "address"
      },
      {
        "internalType": "uint256",
        "name": "tokenAmountIn",
        "type": "uint256"
      },
      {
        "internalType": "uint256",
        "name": "minPoolAmountOut",
        "type": "uint256"
      }
    ],
    "name": "getFoldAmountOutSingle",
    "outputs": [
      {
        "internalType": "uint256",
        "name": "poolAmountOut",
        "type": "uint256"
      }
    ],
    "stateMutability": "view",
    "type": "function"
  },
  {
    "inputs": [
      {
        "internalType": "address",
        "name": "tokenOut",
        "type": "address"
      },
      {
        "internalType": "uint256",
        "name": "poolAmountIn",
        "type": "uint256"
      },
      {
        "internalType": "uint256",
        "name": "minTokenAmountOut",
        "type": "uint256"
      }
    ],
    "name": "getTokenAmountOutSingle",
    "outputs": [
      {
        "internalType": "uint256",
        "name": "tokenAmountOut",
        "type": "uint256"
      }
    ],
    "stateMutability": "view",
    "type": "function"
  },
  {
    "inputs": [],
    "name": "getTokenWeights",
    "outputs": [
      {
        "internalType": "uint256[]",
        "name": "",
        "type": "uint256[]"
      }
    ],
    "stateMutability": "view",
    "type": "function"
  },
  {
    "inputs": [
      {
        "internalType": "uint256",
        "name": "poolAmountOut",
        "type": "uint256"
      },
      {
        "internalType": "uint256[]",
        "name": "maxAmountsIn",
        "type": "uint256[]"
      }
    ],
    "name": "getTokensAmountIn",
    "outputs": [
      {
        "internalType": "uint256[]",
        "name": "actualAmountsIn",
        "type": "uint256[]"
      }
    ],
    "stateMutability": "view",
    "type": "function"
  },
  {
    "inputs": [
      {
        "internalType": "uint256",
        "name": "poolAmountIn",
        "type": "uint256"
      },
      {
        "internalType": "uint256[]",
        "name": "minAmountsOut",
        "type": "uint256[]"
      }
    ],
    "name": "getTokensAmountOut",
    "outputs": [
      {
        "internalType": "uint256[]",
        "name": "actualAmountsOut",
        "type": "uint256[]"
      }
    ],
    "stateMutability": "view",
    "type": "function"
  },
  {
    "inputs": [
      {
        "internalType": "address",
        "name": "liquidatedUser",
        "type": "address"
      },
      {
        "internalType": "address",
        "name": "tokenOut",
        "type": "address"
      },
      {
        "internalType": "uint256",
        "name": "poolAmountIn",
        "type": "uint256"
      },
      {
        "internalType": "uint256",
        "name": "minAmountOut",
        "type": "uint256"
      }
    ],
    "name": "liquidate",
    "outputs": [],
    "stateMutability": "nonpayable",
    "type": "function"
  },
  {
    "inputs": [],
    "name": "protocolFee",
    "outputs": [
      {
        "internalType": "uint256",
        "name": "",
        "type": "uint256"
      }
    ],
    "stateMutability": "view",
    "type": "function"
  },
  {
    "inputs": [],
    "name": "DictatorDAO",
    "outputs": [
      {
        "internalType": "address",
        "name": "",
        "type": "address"
      }
    ],
    "stateMutability": "view",
    "type": "function"
  },
  {
    "inputs": [],
    "name": "smartPool",
    "outputs": [
      {
        "internalType": "contract ISmartPool",
        "name": "",
        "type": "address"
      }
    ],
    "stateMutability": "view",
    "type": "function"
  },
  {
    "inputs": [],
    "name": "foldToken",
    "outputs": [
      {
        "internalType": "contract IMintableERC20",
        "name": "",
        "type": "address"
      }
    ],
    "stateMutability": "view",
    "type": "function"
  },
  {
    "inputs": [],
    "name": "treasury",
    "outputs": [
      {
        "internalType": "address",
        "name": "",
        "type": "address"
      }
    ],
    "stateMutability": "view",
    "type": "function"
  },
  {
    "inputs": [
      {
        "internalType": "address",
        "name": "tokenOut",
        "type": "address"
      },
      {
        "internalType": "uint256",
        "name": "poolAmountIn",
        "type": "uint256"
      },
      {
        "internalType": "uint256",
        "name": "minAmountOut",
        "type": "uint256"
      }
    ],
    "name": "withdraw",
    "outputs": [],
    "stateMutability": "nonpayable",
    "type": "function"
  },
  {
    "inputs": [
      {
        "internalType": "uint256",
        "name": "poolAmountIn",
        "type": "uint256"
      },
      {
        "internalType": "uint256[]",
        "name": "minAmountsOut",
        "type": "uint256[]"
      }
    ],
    "name": "withdrawAll",
    "outputs": [],
    "stateMutability": "nonpayable",
    "type": "function"
  },
  {
    "inputs": [],
    "name": "wrappingContract",
    "outputs": [
      {
        "internalType": "contract IFoldWrapper",
        "name": "",
        "type": "address"
      }
    ],
    "stateMutability": "view",
    "type": "function"
  }
]
